flask_url_mapping/__init__.py
flask_url_mapping/flask_urls.py
flask_url_mapping-0.6.dist-info/LICENSE
flask_url_mapping-0.6.dist-info/METADATA
flask_url_mapping-0.6.dist-info/WHEEL
flask_url_mapping-0.6.dist-info/top_level.txt
flask_url_mapping-0.6.dist-info/RECORD
